gtf/__init__.py
gtf/main.py
gtf/utils.py
gtf-0.0.6.dist-info/LICENSE
gtf-0.0.6.dist-info/METADATA
gtf-0.0.6.dist-info/WHEEL
gtf-0.0.6.dist-info/entry_points.txt
gtf-0.0.6.dist-info/top_level.txt
gtf-0.0.6.dist-info/RECORD
