Metadata-Version: 2.1
Name: gtf
Version: 0.0.6
Summary: A GTF installer is a command line tool that quickly and efficiently installs software and libraries while managing software dependencies. It's essential for deployment and development pipelines and automates the installation process.
Home-page: https://github.com/GreyTechno/gtf
Author: MR_GT
Author-email: friendyt89@gmail.com
License: MIT
Keywords: installer,gtf,cli,software,libraries,packagemanagers,dependencies,automation,deploymentpipeline
Classifier: Development Status :: 4 - Beta
Classifier: Intended Audience :: Developers
Classifier: Topic :: Software Development :: Libraries :: Python Modules
Classifier: License :: OSI Approved :: MIT License
Classifier: Programming Language :: Python :: 3
Classifier: Operating System :: OS Independent
Classifier: Environment :: Console
Requires-Python: >=3.5
License-File: LICENSE
Requires-Dist: requests
Requires-Dist: random2
